Metadata-Version: 2.1
Name: python-cli-rucod
Version: 1.0.2
Summary: Package for create cli on Python
Author: RuCodinger
Author-email: rucodinger@gmail.com
